.gitignore
CHANGELOG.md
Dockerfile
LICENSE
MANIFEST.in
README.md
setup.py
.github/test_wisdom.py
.github/workflows/deploy.yml
.github/workflows/main.yml
griznog/__init__.py
griznog/body.py
griznog/client.py
griznog/utils.py
griznog/version.py
griznog/wisdom.py
griznog.egg-info/PKG-INFO
griznog.egg-info/SOURCES.txt
griznog.egg-info/dependency_links.txt
griznog.egg-info/entry_points.txt
griznog.egg-info/not-zip-safe
griznog.egg-info/top_level.txt